constec/erp/__init__.py
constec/erp/client.py
constec/erp/easy.py
constec/erp/errors.py
constec/erp/types.py
constec/erp/api/__init__.py
constec/erp/api/connection/__init__.py
constec/erp/api/connection/test_connection_erp_v1_connection_test_post.py
constec/erp/api/customers/__init__.py
constec/erp/api/customers/get_customer_erp_v1_customers_customer_id_get.py
constec/erp/api/customers/list_customers_erp_v1_customers_get.py
constec/erp/api/default/__init__.py
constec/erp/api/default/health_check_erp_v1_health_get.py
constec/erp/api/query/__init__.py
constec/erp/api/query/execute_query_erp_v1_query_post.py
constec/erp/api/sellers/__init__.py
constec/erp/api/sellers/get_seller_erp_v1_sellers_seller_id_get.py
constec/erp/api/sellers/list_sellers_erp_v1_sellers_get.py
constec/erp/api/suppliers/__init__.py
constec/erp/api/suppliers/get_supplier_erp_v1_suppliers_supplier_id_get.py
constec/erp/api/suppliers/list_suppliers_erp_v1_suppliers_get.py
constec/erp/models/__init__.py
constec/erp/models/customer_schema.py
constec/erp/models/http_validation_error.py
constec/erp/models/paginated_response_customer_schema.py
constec/erp/models/paginated_response_seller_schema.py
constec/erp/models/paginated_response_supplier_schema.py
constec/erp/models/query_request.py
constec/erp/models/query_response.py
constec/erp/models/query_response_data_item.py
constec/erp/models/seller_schema.py
constec/erp/models/supplier_schema.py
constec/erp/models/test_connection_request.py
constec/erp/models/test_connection_response.py
constec/erp/models/validation_error.py
constec_erp-0.1.2.dist-info/licenses/LICENSE
constec_erp-0.1.2.dist-info/METADATA
constec_erp-0.1.2.dist-info/WHEEL
constec_erp-0.1.2.dist-info/top_level.txt
constec_erp-0.1.2.dist-info/RECORD
